dkdc-0.50.0.dist-info/METADATA
dkdc-0.50.0.dist-info/WHEEL
dkdc-0.50.0.dist-info/entry_points.txt
dkdc-0.50.0.dist-info/licenses/LICENSE
dkdc/__init__.py
dkdc/_dkdc.cpython-313-darwin.so
dkdc/cli/__init__.py
dkdc/cli/main.py
dkdc-0.50.0.dist-info/RECORD
