Metadata-Version: 2.4
Name: dkdc
Version: 0.50.0
Classifier: Development Status :: 3 - Alpha
Classifier: Programming Language :: Python :: 3.13
Classifier: Programming Language :: Rust
Classifier: License :: OSI Approved :: MIT License
License-File: LICENSE
Summary: don't know, don't care
Author-email: Cody <cody@dkdc.dev>
License: MIT
Requires-Python: >=3.13
